{
  "N_board": 13,
  "n_parts_sum": 50,
  "used_area_sum": 2805462.0,
  "waste_area_sum": 444538.0,
  "board_area_sum": 3250000.0,
  "U_avg": 0.863219076923077,
  "U_avg_excl_last": 0.884256,
  "U_avg_excl_last2": 0.9001941818181818,
  "U_global": 0.863219076923077,
  "U_last": 0.610776,
  "U_worst_excl_last": 0.708936,
  "U_best_board": 0.959688,
  "U_worst_board": 0.610776,
  "last2_used_equiv": 1.319712,
  "sparse_board_count": 0,
  "tail_waste_area": 97306.0,
  "case": "generalization_public_1seed_300s__gcut8",
  "variant": "baseline_greedy",
  "seed": 1000,
  "N_input": 50,
  "runtime_s": 0.34003050000001167,
  "part_area_sum": 2805462.0,
  "board_area_effective": 250000.0,
  "LB_area": 12,
  "N_board_gap_to_LB": 1.0,
  "solver_kind": "baseline_greedy",
  "baseline_order": "area_aspect_desc",
  "decode_cache_hits": 0.0,
  "decode_cache_misses": 50.0,
  "decode_cache_entries": 50.0,
  "micro_cache_hits": 0.0,
  "micro_cache_misses": 552.0,
  "micro_cache_entries": 552.0,
  "solver_role": "",
  "solver_bundle": "",
  "preprocess_distinct_shapes": 50,
  "preprocess_duplicate_parts": 0,
  "preprocess_large_part_count": 39,
  "preprocess_strip_part_count": 0,
  "preprocess_quantized_parts": 0,
  "main_profile_tier": "base",
  "main_profile_n_parts": 50,
  "main_profile_lb_area": 12,
  "resume_cache_hit": 0
}