{
  "N_board": 2,
  "n_parts_sum": 23,
  "used_area_sum": 4344.0,
  "waste_area_sum": 1256.0,
  "board_area_sum": 5600.0,
  "U_avg": 0.7757142857142857,
  "U_avg_excl_last": 0.8807142857142857,
  "U_avg_excl_last2": 0.8807142857142857,
  "U_global": 0.7757142857142857,
  "U_last": 0.6707142857142857,
  "U_worst_excl_last": 0.8807142857142857,
  "U_best_board": 0.8807142857142857,
  "U_worst_board": 0.6707142857142857,
  "last2_used_equiv": 1.5514285714285714,
  "sparse_board_count": 0,
  "tail_waste_area": 922.0,
  "case": "generalization_public_1seed_300s__cgcut2",
  "variant": "baseline_greedy",
  "seed": 1000,
  "N_input": 23,
  "runtime_s": 0.0094785,
  "part_area_sum": 4344.0,
  "board_area_effective": 2800.0,
  "LB_area": 2,
  "N_board_gap_to_LB": 0.0,
  "solver_kind": "baseline_greedy",
  "baseline_order": "area_aspect_desc",
  "decode_cache_hits": 0.0,
  "decode_cache_misses": 23.0,
  "decode_cache_entries": 23.0,
  "micro_cache_hits": 22.0,
  "micro_cache_misses": 38.0,
  "micro_cache_entries": 38.0,
  "solver_role": "",
  "solver_bundle": "",
  "preprocess_distinct_shapes": 10,
  "preprocess_duplicate_parts": 13,
  "preprocess_large_part_count": 2,
  "preprocess_strip_part_count": 0,
  "preprocess_quantized_parts": 0,
  "main_profile_tier": "base",
  "main_profile_n_parts": 23,
  "main_profile_lb_area": 2,
  "resume_cache_hit": 0
}